mcp_chat_insight/__init__.py
mcp_chat_insight/prompt.py
mcp_chat_insight/prompt_detached.py
mcp_chat_insight/server.py
mcp_chat_insight-0.2.0.dist-info/METADATA
mcp_chat_insight-0.2.0.dist-info/WHEEL
mcp_chat_insight-0.2.0.dist-info/entry_points.txt
mcp_chat_insight-0.2.0.dist-info/licenses/LICENSE
mcp_chat_insight-0.2.0.dist-info/RECORD
