Metadata-Version: 2.4
Name: mcp-chat-insight
Version: 0.2.0
Summary: MCP Chat Insight Server
License-File: LICENSE
Requires-Python: >=3.11
Requires-Dist: aiomysql>=0.2.0
Requires-Dist: fastmcp>=2.2.7
